{
  "uid": "s:40~l:59~e:draft~y:2022",
  "year": 2022,
  "displayName": "2022 Women's National Basketball Association Draft",
  "shortDisplayName": "2022 WNBA Draft",
  "positions": [
    {
      "id": "9",
      "displayName": "Center",
      "abbreviation": "C"
    },
    {
      "id": "5",
      "displayName": "Small Forward",
      "abbreviation": "SF"
    },
    {
      "id": "6",
      "displayName": "Power Forward",
      "abbreviation": "PF"
    },
    {
      "id": "1",
      "displayName": "Point Guard",
      "abbreviation": "PG"
    },
    {
      "id": "2",
      "displayName": "Shooting Guard",
      "abbreviation": "SG"
    }
  ],
  "rounds": 3,
  "status": {
    "round": 3,
    "state": "post",
    "name": "COMPLETED",
    "description": "Completed"
  },
  "broadcasts": [],
  "picks": [
    {
      "status": "SELECTION_MADE",
      "pick": 1,
      "overall": 1,
      "round": 1,
      "traded": true,
      "tradeNote": "From WSH",
      "athlete": {
        "id": "106158",
        "displayName": "Rhyne Howard",
        "displayHeight": "6'2\"",
        "headshot": {
          "href": "https://a.espncdn.com/i/headshots/wnbadraft/players/full/106158.png"
        },
        "position": {
          "id": "2"
        },
        "team": {
          "location": "Kentucky",
          "name": "Wildcats",
          "abbreviation": "UK",
          "shortDisplayName": "Kentucky"
        },
        "attributes": [
          {
            "name": "rank",
            "displayName": "Rank",
            "abbreviation": "POS RK",
            "displayValue": "1"
          },
          {
            "name": "overall",
            "displayName": "Overall",
            "abbreviation": "OVR RK",
            "displayValue": "2"
          }
        ],
        "guid": "940914f8-5293-4fb8-0f4c-7c5436f2c5bd",
        "alternativeId": "4398674",
        "link": "https://www.espn.com/wnba/player/_/id/4398674/rhyne-howard",
        "proLink": "https://www.espn.com/wnba/player/_/id/4398674/rhyne-howard",
        "uid": "s:40~l:59~a:4398674"
      },
      "teamId": "20"
    },
    {
      "status": "SELECTION_MADE",
      "pick": 2,
      "overall": 2,
      "round": 1,
      "traded": false,
      "athlete": {
        "id": "106157",
        "displayName": "NaLyssa Smith",
        "displayHeight": "6'2\"",
        "headshot": {
          "href": "https://a.espncdn.com/i/headshots/wnbadraft/players/full/106157.png"
        },
        "position": {
          "id": "6"
        },
        "team": {
          "location": "Baylor",
          "name": "Bears",
          "abbreviation": "BAY",
          "shortDisplayName": "Baylor"
        },
        "attributes": [
          {
            "name": "rank",
            "displayName": "Rank",
            "abbreviation": "POS RK",
            "displayValue": "1"
          },
          {
            "name": "overall",
            "displayName": "Overall",
            "abbreviation": "OVR RK",
            "displayValue": "1"
          }
        ],
        "guid": "92bac4f9-e4db-67c6-0354-24c06720f754",
        "alternativeId": "4398776",
        "link": "https://www.espn.com/wnba/player/_/id/4398776/nalyssa-smith",
        "proLink": "https://www.espn.com/wnba/player/_/id/4398776/nalyssa-smith",
        "uid": "s:40~l:59~a:4398776"
      },
      "teamId": "5"
    },
    {
      "status": "SELECTION_MADE",
      "pick": 3,
      "overall": 3,
      "round": 1,
      "traded": true,
      "tradeNote": "From ATL",
      "athlete": {
        "id": "106159",
        "displayName": "Shakira Austin",
        "displayHeight": "6'5\"",
        "headshot": {
          "href": "https://a.espncdn.com/i/headshots/wnbadraft/players/full/106159.png"
        },
        "position": {
          "id": "9"
        },
        "team": {
          "location": "Ole Miss",
          "name": "Rebels",
          "abbreviation": "MISS",
          "shortDisplayName": "Ole Miss"
        },
        "attributes": [
          {
            "name": "rank",
            "displayName": "Rank",
            "abbreviation": "POS RK",
            "displayValue": "1"
          },
          {
            "name": "overall",
            "displayName": "Overall",
            "abbreviation": "OVR RK",
            "displayValue": "3"
          }
        ],
        "guid": "0390235b-d63b-9a48-470f-dc80c05a20fa",
        "alternativeId": "4398911",
        "link": "https://www.espn.com/wnba/player/_/id/4398911/shakira-austin",
        "proLink": "https://www.espn.com/wnba/player/_/id/4398911/shakira-austin",
        "uid": "s:40~l:59~a:4398911"
      },
      "teamId": "16"
    },
    {
      "status": "SELECTION_MADE",
      "pick": 4,
      "overall": 4,
      "round": 1,
      "traded": true,
      "tradeNote": "From LA",
      "athlete": {
        "id": "106162",
        "displayName": "Emily Engstler",
        "displayHeight": "6'1\"",
        "headshot": {
          "href": "https://a.espncdn.com/i/headshots/wnbadraft/players/full/106162.png"
        },
        "position": {
          "id": "6"
        },
        "team": {
          "location": "Louisville",
          "name": "Cardinals",
          "abbreviation": "LOU",
          "shortDisplayName": "Louisville"
        },
        "attributes": [
          {
            "name": "rank",
            "displayName": "Rank",
            "abbreviation": "POS RK",
            "displayValue": "2"
          },
          {
            "name": "overall",
            "displayName": "Overall",
            "abbreviation": "OVR RK",
            "displayValue": "6"
          }
        ],
        "guid": "b2eb4e85-2965-f2b9-519a-c12058d48430",
        "alternativeId": "4398729",
        "link": "https://www.espn.com/wnba/player/_/id/4398729/emily-engstler",
        "proLink": "https://www.espn.com/wnba/player/_/id/4398729/emily-engstler",
        "uid": "s:40~l:59~a:4398729"
      },
      "teamId": "5"
    },
    {
      "status": "SELECTION_MADE",
      "pick": 5,
      "overall": 5,
      "round": 1,
      "traded": false,
      "athlete": {
        "id": "106160",
        "displayName": "Nyara Sabally",
        "displayHeight": "6'5\"",
        "position": {
          "id": "9"
        },
        "team": {
          "location": "Oregon",
          "name": "Ducks",
          "abbreviation": "ORE",
          "shortDisplayName": "Oregon"
        },
        "attributes": [
          {
            "name": "rank",
            "displayName": "Rank",
            "abbreviation": "POS RK",
            "displayValue": "2"
          },
          {
            "name": "overall",
            "displayName": "Overall",
            "abbreviation": "OVR RK",
            "displayValue": "4"
          }
        ],
        "guid": "d802dec8-8c30-07a9-d761-20123ed66d35",
        "alternativeId": "4398768",
        "headshot": {
          "href": "https://a.espncdn.com/i/headshots/womens-college-basketball/players/full/4398768.png"
        },
        "link": "https://www.espn.com/wnba/player/_/id/4398768/nyara-sabally",
        "proLink": "https://www.espn.com/wnba/player/_/id/4398768/nyara-sabally",
        "uid": "s:40~l:59~a:4398768"
      },
      "teamId": "9"
    },
    {
      "status": "SELECTION_MADE",
      "pick": 6,
      "overall": 6,
      "round": 1,
      "traded": true,
      "tradeNote": "From DAL",
      "athlete": {
        "id": "106174",
        "displayName": "Lexie Hull",
        "displayHeight": "6'1\"",
        "headshot": {
          "href": "https://a.espncdn.com/i/headshots/wnbadraft/players/full/106174.png"
        },
        "position": {
          "id": "2"
        },
        "team": {
          "location": "Stanford",
          "name": "Cardinal",
          "abbreviation": "STAN",
          "shortDisplayName": "Stanford"
        },
        "attributes": [
          {
            "name": "rank",
            "displayName": "Rank",
            "abbreviation": "POS RK",
            "displayValue": "4"
          },
          {
            "name": "overall",
            "displayName": "Overall",
            "abbreviation": "OVR RK",
            "displayValue": "17"
          }
        ],
        "guid": "a27d443a-9d18-a215-5e1d-d4090cd1358d",
        "alternativeId": "4398829",
        "link": "https://www.espn.com/wnba/player/_/id/4398829/lexie-hull",
        "proLink": "https://www.espn.com/wnba/player/_/id/4398829/lexie-hull",
        "uid": "s:40~l:59~a:4398829"
      },
      "teamId": "5"
    },
    {
      "status": "SELECTION_MADE",
      "pick": 7,
      "overall": 7,
      "round": 1,
      "traded": true,
      "tradeNote": "From CHI",
      "athlete": {
        "id": "106170",
        "displayName": "Veronica Burton",
        "displayHeight": "5'9\"",
        "headshot": {
          "href": "https://a.espncdn.com/i/headshots/wnbadraft/players/full/106170.png"
        },
        "position": {
          "id": "1"
        },
        "team": {
          "location": "Northwestern",
          "name": "Wildcats",
          "abbreviation": "NU",
          "shortDisplayName": "Northwestern"
        },
        "attributes": [
          {
            "name": "rank",
            "displayName": "Rank",
            "abbreviation": "POS RK",
            "displayValue": "1"
          },
          {
            "name": "overall",
            "displayName": "Overall",
            "abbreviation": "OVR RK",
            "displayValue": "13"
          }
        ],
        "guid": "3cfb5941-68e7-722a-4525-aca3d5bdfb66",
        "alternativeId": "4398935",
        "link": "https://www.espn.com/wnba/player/_/id/4398935/veronica-burton",
        "proLink": "https://www.espn.com/wnba/player/_/id/4398935/veronica-burton",
        "uid": "s:40~l:59~a:4398935"
      },
      "teamId": "3"
    },
    {
      "status": "SELECTION_MADE",
      "pick": 8,
      "overall": 8,
      "round": 1,
      "traded": true,
      "tradeNote": "From MIN",
      "athlete": {
        "id": "106181",
        "displayName": "Mya Hollingshed",
        "displayHeight": "6'3\"",
        "headshot": {
          "href": "https://a.espncdn.com/i/headshots/wnbadraft/players/full/106181.png"
        },
        "position": {
          "id": "5"
        },
        "team": {
          "location": "Colorado",
          "name": "Buffaloes",
          "abbreviation": "COLO",
          "shortDisplayName": "Colorado"
        },
        "attributes": [
          {
            "name": "rank",
            "displayName": "Rank",
            "abbreviation": "POS RK",
            "displayValue": "2"
          },
          {
            "name": "overall",
            "displayName": "Overall",
            "abbreviation": "OVR RK",
            "displayValue": "23"
          }
        ],
        "guid": "f5fba0f9-01e0-ebc9-820f-0907bac7b3e3",
        "alternativeId": "4281923",
        "link": "https://www.espn.com/wnba/player/_/id/4281923/mya-hollingshed",
        "proLink": "https://www.espn.com/wnba/player/_/id/4281923/mya-hollingshed",
        "uid": "s:40~l:59~a:4281923"
      },
      "teamId": "17"
    },
    {
      "status": "SELECTION_MADE",
      "pick": 9,
      "overall": 9,
      "round": 1,
      "traded": true,
      "tradeNote": "From SEA",
      "athlete": {
        "id": "106163",
        "displayName": "Rae Burrell",
        "displayHeight": "6'1\"",
        "headshot": {
          "href": "https://a.espncdn.com/i/headshots/wnbadraft/players/full/106163.png"
        },
        "position": {
          "id": "5"
        },
        "team": {
          "location": "Tennessee",
          "name": "Lady Volunteers",
          "abbreviation": "TENN",
          "shortDisplayName": "Tennessee"
        },
        "attributes": [
          {
            "name": "rank",
            "displayName": "Rank",
            "abbreviation": "POS RK",
            "displayValue": "1"
          },
          {
            "name": "overall",
            "displayName": "Overall",
            "abbreviation": "OVR RK",
            "displayValue": "7"
          }
        ],
        "guid": "f3042c82-faad-5d6f-5e5c-6c7930590621",
        "alternativeId": "4398764",
        "link": "https://www.espn.com/wnba/player/_/id/4398764/rae-burrell",
        "proLink": "https://www.espn.com/wnba/player/_/id/4398764/rae-burrell",
        "uid": "s:40~l:59~a:4398764"
      },
      "teamId": "6"
    },
    {
      "status": "SELECTION_MADE",
      "pick": 10,
      "overall": 10,
      "round": 1,
      "traded": true,
      "tradeNote": "From MIN",
      "athlete": {
        "id": "106168",
        "displayName": "Queen Egbo",
        "displayHeight": "6'3\"",
        "headshot": {
          "href": "https://a.espncdn.com/i/headshots/wnbadraft/players/full/106168.png"
        },
        "position": {
          "id": "9"
        },
        "team": {
          "location": "Baylor",
          "name": "Bears",
          "abbreviation": "BAY",
          "shortDisplayName": "Baylor"
        },
        "attributes": [
          {
            "name": "rank",
            "displayName": "Rank",
            "abbreviation": "POS RK",
            "displayValue": "4"
          },
          {
            "name": "overall",
            "displayName": "Overall",
            "abbreviation": "OVR RK",
            "displayValue": "11"
          }
        ],
        "guid": "e91e9d02-26be-7bf2-4fd9-8fdf1e1864e8",
        "alternativeId": "4398779",
        "link": "https://www.espn.com/wnba/player/_/id/4398779/queen-egbo",
        "proLink": "https://www.espn.com/wnba/player/_/id/4398779/queen-egbo",
        "uid": "s:40~l:59~a:4398779"
      },
      "teamId": "5"
    },
    {
      "status": "SELECTION_MADE",
      "pick": 11,
      "overall": 11,
      "round": 1,
      "traded": false,
      "athlete": {
        "id": "106169",
        "displayName": "Kierstan Bell",
        "displayHeight": "6'1\"",
        "headshot": {
          "href": "https://a.espncdn.com/i/headshots/wnbadraft/players/full/106169.png"
        },
        "position": {
          "id": "2"
        },
        "team": {
          "location": "Florida Gulf Coast",
          "name": "Eagles",
          "abbreviation": "FGCU",
          "shortDisplayName": "FGCU"
        },
        "attributes": [
          {
            "name": "rank",
            "displayName": "Rank",
            "abbreviation": "POS RK",
            "displayValue": "3"
          },
          {
            "name": "overall",
            "displayName": "Overall",
            "abbreviation": "OVR RK",
            "displayValue": "12"
          }
        ],
        "guid": "7923526e-bc15-3288-9363-4a77de99bd64",
        "alternativeId": "4433633",
        "link": "https://www.espn.com/wnba/player/_/id/4433633/kierstan-bell",
        "proLink": "https://www.espn.com/wnba/player/_/id/4433633/kierstan-bell",
        "uid": "s:40~l:59~a:4433633"
      },
      "teamId": "17"
    },
    {
      "status": "SELECTION_MADE",
      "pick": 12,
      "overall": 12,
      "round": 1,
      "traded": false,
      "athlete": {
        "id": "106176",
        "displayName": "Nia Clouden",
        "displayHeight": "5'8\"",
        "headshot": {
          "href": "https://a.espncdn.com/i/headshots/wnbadraft/players/full/106176.png"
        },
        "position": {
          "id": "2"
        },
        "team": {
          "location": "Michigan State",
          "name": "Spartans",
          "abbreviation": "MSU",
          "shortDisplayName": "Michigan St"
        },
        "attributes": [
          {
            "name": "rank",
            "displayName": "Rank",
            "abbreviation": "POS RK",
            "displayValue": "5"
          },
          {
            "name": "overall",
            "displayName": "Overall",
            "abbreviation": "OVR RK",
            "displayValue": "19"
          }
        ],
        "guid": "e597cbf0-a3ed-5eda-9052-0d0a21bf083b",
        "alternativeId": "4398921",
        "link": "https://www.espn.com/wnba/player/_/id/4398921/nia-clouden",
        "proLink": "https://www.espn.com/wnba/player/_/id/4398921/nia-clouden",
        "uid": "s:40~l:59~a:4398921"
      },
      "teamId": "18"
    },
    {
      "status": "SELECTION_MADE",
      "pick": 1,
      "overall": 13,
      "round": 2,
      "traded": true,
      "tradeNote": "From MIN",
      "athlete": {
        "id": "106177",
        "displayName": "Khayla Pointer",
        "headshot": {
          "href": "https://a.espncdn.com/i/headshots/wnbadraft/players/full/106177.png"
        },
        "position": {
          "id": "1"
        },
        "team": {
          "location": "LSU",
          "name": "Tigers",
          "abbreviation": "LSU",
          "shortDisplayName": "LSU"
        },
        "attributes": [
          {
            "name": "rank",
            "displayName": "Rank",
            "abbreviation": "POS RK",
            "displayValue": "4"
          },
          {
            "name": "overall",
            "displayName": "Overall",
            "abbreviation": "OVR RK",
            "displayValue": "20"
          }
        ],
        "guid": "d91377aa-4aca-304f-099f-183d220eebb9",
        "alternativeId": "4280859",
        "link": "https://www.espn.com/wnba/player/_/id/4280859/khayla-pointer",
        "proLink": "https://www.espn.com/wnba/player/_/id/4280859/khayla-pointer",
        "uid": "s:40~l:59~a:4280859"
      },
      "teamId": "17"
    },
    {
      "status": "SELECTION_MADE",
      "pick": 2,
      "overall": 14,
      "round": 2,
      "traded": false,
      "tradeNote": "From ATL",
      "athlete": {
        "id": "106165",
        "displayName": "Christyn Williams",
        "displayHeight": "5'11\"",
        "headshot": {
          "href": "https://a.espncdn.com/i/headshots/wnbadraft/players/full/106165.png"
        },
        "position": {
          "id": "2"
        },
        "team": {
          "location": "UConn",
          "name": "Huskies",
          "abbreviation": "CONN",
          "shortDisplayName": "UConn"
        },
        "attributes": [
          {
            "name": "rank",
            "displayName": "Rank",
            "abbreviation": "POS RK",
            "displayValue": "2"
          },
          {
            "name": "overall",
            "displayName": "Overall",
            "abbreviation": "OVR RK",
            "displayValue": "8"
          }
        ],
        "guid": "517e74ee-d98f-d504-2daf-1504e47254bb",
        "alternativeId": "4398965",
        "link": "https://www.espn.com/wnba/player/_/id/4398965/christyn-williams",
        "proLink": "https://www.espn.com/wnba/player/_/id/4398965/christyn-williams",
        "uid": "s:40~l:59~a:4398965"
      },
      "teamId": "16"
    },
    {
      "status": "SELECTION_MADE",
      "pick": 3,
      "overall": 15,
      "round": 2,
      "traded": true,
      "tradeNote": "From LA",
      "athlete": {
        "id": "106167",
        "displayName": "Naz Hillmon",
        "displayHeight": "6'2\"",
        "headshot": {
          "href": "https://a.espncdn.com/i/headshots/wnbadraft/players/full/106167.png"
        },
        "position": {
          "id": "6"
        },
        "team": {
          "location": "Michigan",
          "name": "Wolverines",
          "abbreviation": "MICH",
          "shortDisplayName": "Michigan"
        },
        "attributes": [
          {
            "name": "rank",
            "displayName": "Rank",
            "abbreviation": "POS RK",
            "displayValue": "4"
          },
          {
            "name": "overall",
            "displayName": "Overall",
            "abbreviation": "OVR RK",
            "displayValue": "10"
          }
        ],
        "guid": "55b8c3a3-d957-b4d9-c706-2e25909a1324",
        "alternativeId": "4398915",
        "link": "https://www.espn.com/wnba/player/_/id/4398915/naz-hillmon",
        "proLink": "https://www.espn.com/wnba/player/_/id/4398915/naz-hillmon",
        "uid": "s:40~l:59~a:4398915"
      },
      "teamId": "20"
    },
    {
      "status": "SELECTION_MADE",
      "pick": 4,
      "overall": 16,
      "round": 2,
      "traded": true,
      "tradeNote": "From WAS",
      "athlete": {
        "id": "106186",
        "displayName": "Kianna Smith",
        "displayHeight": "6'0\"",
        "headshot": {
          "href": "https://a.espncdn.com/i/headshots/wnbadraft/players/full/106186.png"
        },
        "position": {
          "id": "2"
        },
        "team": {
          "location": "Louisville",
          "name": "Cardinals",
          "abbreviation": "LOU",
          "shortDisplayName": "Louisville"
        },
        "attributes": [
          {
            "name": "rank",
            "displayName": "Rank",
            "abbreviation": "POS RK",
            "displayValue": "7"
          },
          {
            "name": "overall",
            "displayName": "Overall",
            "abbreviation": "OVR RK",
            "displayValue": "28"
          }
        ],
        "guid": "98d26903-dea1-f2b2-6384-ef6094bb860a",
        "alternativeId": "4281919",
        "link": "https://www.espn.com/wnba/player/_/id/4281919/kianna-smith",
        "proLink": "https://www.espn.com/wnba/player/_/id/4281919/kianna-smith",
        "uid": "s:40~l:59~a:4281919"
      },
      "teamId": "6"
    },
    {
      "status": "SELECTION_MADE",
      "pick": 5,
      "overall": 17,
      "round": 2,
      "traded": true,
      "tradeNote": "From NY",
      "athlete": {
        "id": "106213",
        "displayName": "Elissa Cunane",
        "displayHeight": "6'5\"",
        "position": {
          "id": "9"
        },
        "team": {
          "location": "NC State",
          "name": "Wolfpack",
          "abbreviation": "NCSU",
          "shortDisplayName": "NC State"
        },
        "attributes": [
          {
            "name": "rank",
            "displayName": "Rank",
            "abbreviation": "POS RK",
            "displayValue": "3"
          },
          {
            "name": "overall",
            "displayName": "Overall",
            "abbreviation": "OVR RK",
            "displayValue": "5"
          }
        ],
        "guid": "3b131a8e-3815-cac1-4ce4-f4b1ce5483da",
        "alternativeId": "4398625",
        "headshot": {
          "href": "https://a.espncdn.com/i/headshots/womens-college-basketball/players/full/4398625.png"
        },
        "link": "https://www.espn.com/wnba/player/_/id/4398625/elissa-cunane",
        "proLink": "https://www.espn.com/wnba/player/_/id/4398625/elissa-cunane",
        "uid": "s:40~l:59~a:4398625"
      },
      "teamId": "14"
    },
    {
      "status": "SELECTION_MADE",
      "pick": 6,
      "overall": 18,
      "round": 2,
      "traded": true,
      "tradeNote": "From DAL",
      "athlete": {
        "id": "106171",
        "displayName": "Lorela Cubaj",
        "displayHeight": "6'4\"",
        "headshot": {
          "href": "https://a.espncdn.com/i/headshots/wnbadraft/players/full/106171.png"
        },
        "position": {
          "id": "6"
        },
        "team": {
          "location": "Georgia Tech",
          "name": "Yellow Jackets",
          "abbreviation": "GT",
          "shortDisplayName": "Georgia Tech"
        },
        "attributes": [
          {
            "name": "rank",
            "displayName": "Rank",
            "abbreviation": "POS RK",
            "displayValue": "5"
          },
          {
            "name": "overall",
            "displayName": "Overall",
            "abbreviation": "OVR RK",
            "displayValue": "14"
          }
        ],
        "guid": "ebdd3e72-03ed-aa74-5317-1cdc8f5eec00",
        "alternativeId": "4281183",
        "link": "https://www.espn.com/wnba/player/_/id/4281183/lorela-cubaj",
        "proLink": "https://www.espn.com/wnba/player/_/id/4281183/lorela-cubaj",
        "uid": "s:40~l:59~a:4281183"
      },
      "teamId": "14"
    },
    {
      "status": "SELECTION_MADE",
      "pick": 7,
      "overall": 19,
      "round": 2,
      "traded": true,
      "tradeNote": "From CHI",
      "athlete": {
        "id": "106178",
        "displayName": "Olivia Nelson-Ododa",
        "displayHeight": "6'5\"",
        "headshot": {
          "href": "https://a.espncdn.com/i/headshots/wnbadraft/players/full/106178.png"
        },
        "position": {
          "id": "6"
        },
        "team": {
          "location": "UConn",
          "name": "Huskies",
          "abbreviation": "CONN",
          "shortDisplayName": "UConn"
        },
        "attributes": [
          {
            "name": "rank",
            "displayName": "Rank",
            "abbreviation": "POS RK",
            "displayValue": "6"
          },
          {
            "name": "overall",
            "displayName": "Overall",
            "abbreviation": "OVR RK",
            "displayValue": "21"
          }
        ],
        "guid": "808db7f8-1fd0-9331-db1f-e9dba41e61ab",
        "alternativeId": "4398966",
        "link": "https://www.espn.com/wnba/player/_/id/4398966/olivia-nelson-ododa",
        "proLink": "https://www.espn.com/wnba/player/_/id/4398966/olivia-nelson-ododa",
        "uid": "s:40~l:59~a:4398966"
      },
      "teamId": "6"
    },
    {
      "status": "SELECTION_MADE",
      "pick": 8,
      "overall": 20,
      "round": 2,
      "traded": true,
      "tradeNote": "From PHX",
      "athlete": {
        "id": "106172",
        "displayName": "Destanni Henderson",
        "displayHeight": "5'7\"",
        "headshot": {
          "href": "https://a.espncdn.com/i/headshots/wnbadraft/players/full/106172.png"
        },
        "position": {
          "id": "1"
        },
        "team": {
          "location": "South Carolina",
          "name": "Gamecocks",
          "abbreviation": "SC",
          "shortDisplayName": "South Carolina"
        },
        "attributes": [
          {
            "name": "rank",
            "displayName": "Rank",
            "abbreviation": "POS RK",
            "displayValue": "2"
          },
          {
            "name": "overall",
            "displayName": "Overall",
            "abbreviation": "OVR RK",
            "displayValue": "15"
          }
        ],
        "guid": "10c41d66-b010-751f-044f-f545dc1baabe",
        "alternativeId": "4398751",
        "link": "https://www.espn.com/wnba/player/_/id/4398751/destanni-henderson",
        "proLink": "https://www.espn.com/wnba/player/_/id/4398751/destanni-henderson",
        "uid": "s:40~l:59~a:4398751"
      },
      "teamId": "5"
    },
    {
      "status": "SELECTION_MADE",
      "pick": 9,
      "overall": 21,
      "round": 2,
      "traded": false,
      "athlete": {
        "id": "106173",
        "displayName": "Evina Westbrook",
        "displayHeight": "6'0\"",
        "headshot": {
          "href": "https://a.espncdn.com/i/headshots/wnbadraft/players/full/106173.png"
        },
        "position": {
          "id": "1"
        },
        "team": {
          "location": "UConn",
          "name": "Huskies",
          "abbreviation": "CONN",
          "shortDisplayName": "UConn"
        },
        "attributes": [
          {
            "name": "rank",
            "displayName": "Rank",
            "abbreviation": "POS RK",
            "displayValue": "3"
          },
          {
            "name": "overall",
            "displayName": "Overall",
            "abbreviation": "OVR RK",
            "displayValue": "16"
          }
        ],
        "guid": "eb4b2998-afbb-af0b-a1d7-539dac066d61",
        "alternativeId": "4280890",
        "link": "https://www.espn.com/wnba/player/_/id/4280890/evina-westbrook",
        "proLink": "https://www.espn.com/wnba/player/_/id/4280890/evina-westbrook",
        "uid": "s:40~l:59~a:4280890"
      },
      "teamId": "14"
    },
    {
      "status": "SELECTION_MADE",
      "pick": 10,
      "overall": 22,
      "round": 2,
      "traded": false,
      "athlete": {
        "id": "106215",
        "displayName": "Kayla Jones",
        "displayHeight": "6'1\"",
        "position": {
          "id": "6"
        },
        "team": {
          "location": "NC State",
          "name": "Wolfpack",
          "abbreviation": "NCSU",
          "shortDisplayName": "NC State"
        },
        "attributes": [],
        "guid": "e42c63de-41ec-7b87-9e01-1b5152d34145",
        "alternativeId": "4281199",
        "headshot": {
          "href": "https://a.espncdn.com/i/headshots/womens-college-basketball/players/full/4281199.png"
        },
        "link": "https://www.espn.com/wnba/player/_/id/4281199/kayla-jones",
        "proLink": "https://www.espn.com/wnba/player/_/id/4281199/kayla-jones",
        "uid": "s:40~l:59~a:4281199"
      },
      "teamId": "8"
    },
    {
      "status": "SELECTION_MADE",
      "pick": 11,
      "overall": 23,
      "round": 2,
      "traded": false,
      "athlete": {
        "id": "106183",
        "displayName": "Aisha Sheppard",
        "displayHeight": "5'9\"",
        "headshot": {
          "href": "https://a.espncdn.com/i/headshots/wnbadraft/players/full/106183.png"
        },
        "position": {
          "id": "2"
        },
        "team": {
          "location": "Virginia Tech",
          "name": "Hokies",
          "abbreviation": "VT",
          "shortDisplayName": "Virginia Tech"
        },
        "attributes": [
          {
            "name": "rank",
            "displayName": "Rank",
            "abbreviation": "POS RK",
            "displayValue": "6"
          },
          {
            "name": "overall",
            "displayName": "Overall",
            "abbreviation": "OVR RK",
            "displayValue": "25"
          }
        ],
        "guid": "eb9907dc-415b-8aef-1a61-7c3c234c0234",
        "alternativeId": "4281223",
        "link": "https://www.espn.com/wnba/player/_/id/4281223/aisha-sheppard",
        "proLink": "https://www.espn.com/wnba/player/_/id/4281223/aisha-sheppard",
        "uid": "s:40~l:59~a:4281223"
      },
      "teamId": "17"
    },
    {
      "status": "SELECTION_MADE",
      "pick": 12,
      "overall": 24,
      "round": 2,
      "traded": false,
      "athlete": {
        "id": "106179",
        "displayName": "Jordan Lewis",
        "displayHeight": "5'7\"",
        "headshot": {
          "href": "https://a.espncdn.com/i/headshots/wnbadraft/players/full/106179.png"
        },
        "position": {
          "id": "1"
        },
        "team": {
          "location": "Baylor",
          "name": "Bears",
          "abbreviation": "BAY",
          "shortDisplayName": "Baylor"
        },
        "attributes": [
          {
            "name": "rank",
            "displayName": "Rank",
            "abbreviation": "POS RK",
            "displayValue": "5"
          },
          {
            "name": "overall",
            "displayName": "Overall",
            "abbreviation": "OVR RK",
            "displayValue": "22"
          }
        ],
        "guid": "acb5bed0-53e3-cd2b-6a8c-af751d3357c3",
        "alternativeId": "4065687",
        "link": "https://www.espn.com/wnba/player/_/id/4065687/jordan-lewis",
        "proLink": "https://www.espn.com/wnba/player/_/id/4065687/jordan-lewis",
        "uid": "s:40~l:59~a:4065687"
      },
      "teamId": "18"
    },
    {
      "status": "SELECTION_MADE",
      "pick": 1,
      "overall": 25,
      "round": 3,
      "traded": false,
      "athlete": {
        "id": "106197",
        "displayName": "Ameshya Williams-Holliday",
        "displayHeight": "6'4\"",
        "headshot": {
          "href": "https://a.espncdn.com/i/headshots/wnbadraft/players/full/106197.png"
        },
        "position": {
          "id": "9"
        },
        "team": {
          "location": "Jackson State",
          "name": "Lady Tigers",
          "abbreviation": "JKST",
          "shortDisplayName": "Jackson St"
        },
        "attributes": [
          {
            "name": "rank",
            "displayName": "Rank",
            "abbreviation": "POS RK",
            "displayValue": "6"
          },
          {
            "name": "overall",
            "displayName": "Overall",
            "abbreviation": "OVR RK",
            "displayValue": "36"
          }
        ]
      },
      "teamId": "5"
    },
    {
      "status": "SELECTION_MADE",
      "pick": 2,
      "overall": 26,
      "round": 3,
      "traded": true,
      "tradeNote": "From ATL",
      "athlete": {
        "id": "106190",
        "displayName": "Maya Dodson",
        "displayHeight": "6'3\"",
        "headshot": {
          "href": "https://a.espncdn.com/i/headshots/wnbadraft/players/full/106190.png"
        },
        "position": {
          "id": "6"
        },
        "team": {
          "location": "Notre Dame",
          "name": "Fighting Irish",
          "abbreviation": "ND",
          "shortDisplayName": "Notre Dame"
        },
        "attributes": [
          {
            "name": "rank",
            "displayName": "Rank",
            "abbreviation": "POS RK",
            "displayValue": "7"
          },
          {
            "name": "overall",
            "displayName": "Overall",
            "abbreviation": "OVR RK",
            "displayValue": "30"
          }
        ],
        "guid": "61780b6f-bb76-7b7a-4510-dba781ae435f",
        "alternativeId": "4282166",
        "link": "https://www.espn.com/wnba/player/_/id/4282166/maya-dodson",
        "proLink": "https://www.espn.com/wnba/player/_/id/4282166/maya-dodson",
        "uid": "s:40~l:59~a:4282166"
      },
      "teamId": "11"
    },
    {
      "status": "SELECTION_MADE",
      "pick": 3,
      "overall": 27,
      "round": 3,
      "traded": false,
      "athlete": {
        "id": "106216",
        "displayName": "Amy Atwell",
        "displayHeight": "6'0\"",
        "position": {
          "id": "5"
        },
        "team": {
          "location": "Hawai'i",
          "name": "Rainbow Wahine",
          "abbreviation": "HAW",
          "shortDisplayName": "Hawai'i"
        },
        "attributes": [],
        "guid": "22f9dc1b-5412-b49b-c803-782b67ee58a0",
        "alternativeId": "4068885",
        "headshot": {
          "href": "https://a.espncdn.com/i/headshots/womens-college-basketball/players/full/4068885.png"
        },
        "link": "https://www.espn.com/wnba/player/_/id/4068885/amy-atwell",
        "proLink": "https://www.espn.com/wnba/player/_/id/4068885/amy-atwell",
        "uid": "s:40~l:59~a:4068885"
      },
      "teamId": "6"
    },
    {
      "status": "SELECTION_MADE",
      "pick": 4,
      "overall": 28,
      "round": 3,
      "traded": true,
      "tradeNote": "From WAS",
      "athlete": {
        "id": "106202",
        "displayName": "Hannah Sjerven",
        "displayHeight": "6'2\"",
        "headshot": {
          "href": "https://a.espncdn.com/i/headshots/wnbadraft/players/full/106202.png"
        },
        "position": {
          "id": "6"
        },
        "team": {
          "location": "South Dakota",
          "name": "Coyotes",
          "abbreviation": "SDAK",
          "shortDisplayName": "South Dakota"
        },
        "attributes": [
          {
            "name": "rank",
            "displayName": "Rank",
            "abbreviation": "POS RK",
            "displayValue": "9"
          },
          {
            "name": "overall",
            "displayName": "Overall",
            "abbreviation": "OVR RK",
            "displayValue": "40"
          }
        ],
        "guid": "76aaa74b-28f0-1558-6581-9da0027c48f0",
        "alternativeId": "4068349",
        "link": "https://www.espn.com/wnba/player/_/id/4068349/hannah-sjerven",
        "proLink": "https://www.espn.com/wnba/player/_/id/4068349/hannah-sjerven",
        "uid": "s:40~l:59~a:4068349"
      },
      "teamId": "8"
    },
    {
      "status": "SELECTION_MADE",
      "pick": 5,
      "overall": 29,
      "round": 3,
      "traded": false,
      "athlete": {
        "id": "106166",
        "displayName": "Sika Kone",
        "displayHeight": "6'3\"",
        "headshot": {
          "href": "https://a.espncdn.com/i/headshots/wnbadraft/players/full/106166.png"
        },
        "position": {
          "id": "6"
        },
        "leagueAffiliation": "Mali",
        "attributes": [
          {
            "name": "rank",
            "displayName": "Rank",
            "abbreviation": "POS RK",
            "displayValue": "3"
          },
          {
            "name": "overall",
            "displayName": "Overall",
            "abbreviation": "OVR RK",
            "displayValue": "9"
          }
        ],
        "team": {
          "location": "Mali",
          "name": "Mali",
          "abbreviation": "Mali",
          "shortDisplayName": "Mali"
        }
      },
      "teamId": "9"
    },
    {
      "status": "SELECTION_MADE",
      "pick": 6,
      "overall": 30,
      "round": 3,
      "traded": false,
      "athlete": {
        "id": "106195",
        "displayName": "Jasmine Dickey",
        "displayHeight": "5'10\"",
        "headshot": {
          "href": "https://a.espncdn.com/i/headshots/wnbadraft/players/full/106195.png"
        },
        "position": {
          "id": "5"
        },
        "team": {
          "location": "Delaware",
          "name": "Blue Hens",
          "abbreviation": "DEL",
          "shortDisplayName": "Delaware"
        },
        "attributes": [
          {
            "name": "rank",
            "displayName": "Rank",
            "abbreviation": "POS RK",
            "displayValue": "5"
          },
          {
            "name": "overall",
            "displayName": "Overall",
            "abbreviation": "OVR RK",
            "displayValue": "34"
          }
        ],
        "guid": "64738247-71b9-a1a2-641c-6c83cce1426c",
        "alternativeId": "4399842",
        "link": "https://www.espn.com/wnba/player/_/id/4399842/jasmine-dickey",
        "proLink": "https://www.espn.com/wnba/player/_/id/4399842/jasmine-dickey",
        "uid": "s:40~l:59~a:4399842"
      },
      "teamId": "3"
    },
    {
      "status": "SELECTION_MADE",
      "pick": 7,
      "overall": 31,
      "round": 3,
      "traded": true,
      "tradeNote": "From CHI",
      "athlete": {
        "id": "106217",
        "displayName": "Jazz Bond",
        "displayHeight": "6'4\"",
        "position": {
          "id": "6"
        },
        "team": {
          "location": "North Florida",
          "name": "Ospreys",
          "abbreviation": "UNF",
          "shortDisplayName": "North Florida"
        },
        "attributes": [],
        "guid": "b755a654-9b79-b6ea-84d7-6b6cbf89c56b",
        "alternativeId": "4399879",
        "headshot": {
          "href": "https://a.espncdn.com/i/headshots/womens-college-basketball/players/full/4399879.png"
        },
        "link": "https://www.espn.com/wnba/player/_/id/4399879/jazz-bond",
        "proLink": "https://www.espn.com/wnba/player/_/id/4399879/jazz-bond",
        "uid": "s:40~l:59~a:4399879"
      },
      "teamId": "3"
    },
    {
      "status": "SELECTION_MADE",
      "pick": 8,
      "overall": 32,
      "round": 3,
      "traded": false,
      "athlete": {
        "id": "106194",
        "displayName": "Macee Williams",
        "displayHeight": "6'2\"",
        "headshot": {
          "href": "https://a.espncdn.com/i/headshots/wnbadraft/players/full/106194.png"
        },
        "position": {
          "id": "6"
        },
        "team": {
          "location": "IU Indianapolis",
          "name": "Jaguars",
          "abbreviation": "IUIN",
          "shortDisplayName": "IU Indy"
        },
        "attributes": [
          {
            "name": "rank",
            "displayName": "Rank",
            "abbreviation": "POS RK",
            "displayValue": "8"
          },
          {
            "name": "overall",
            "displayName": "Overall",
            "abbreviation": "OVR RK",
            "displayValue": "33"
          }
        ],
        "guid": "988be84c-bf81-6103-fc63-326878344bed",
        "alternativeId": "4281963",
        "link": "https://www.espn.com/wnba/player/_/id/4281963/macee-williams",
        "proLink": "https://www.espn.com/wnba/player/_/id/4281963/macee-williams",
        "uid": "s:40~l:59~a:4281963"
      },
      "teamId": "11"
    },
    {
      "status": "SELECTION_MADE",
      "pick": 9,
      "overall": 33,
      "round": 3,
      "traded": false,
      "athlete": {
        "id": "106182",
        "displayName": "Jade Melbourne",
        "displayHeight": "5'10\"",
        "headshot": {
          "href": "https://a.espncdn.com/i/headshots/wnbadraft/players/full/106182.png"
        },
        "position": {
          "id": "1"
        },
        "leagueAffiliation": "Australia",
        "attributes": [
          {
            "name": "rank",
            "displayName": "Rank",
            "abbreviation": "POS RK",
            "displayValue": "6"
          },
          {
            "name": "overall",
            "displayName": "Overall",
            "abbreviation": "OVR RK",
            "displayValue": "24"
          }
        ],
        "team": {
          "location": "Australia",
          "name": "Australia",
          "abbreviation": "Australia",
          "shortDisplayName": "Australia"
        }
      },
      "teamId": "14"
    },
    {
      "status": "SELECTION_MADE",
      "pick": 10,
      "overall": 34,
      "round": 3,
      "traded": true,
      "tradeNote": "From MIN",
      "athlete": {
        "id": "106218",
        "displayName": "Ali Patberg",
        "displayHeight": "5'11\"",
        "position": {
          "id": "2"
        },
        "team": {
          "location": "Indiana",
          "name": "Hoosiers",
          "abbreviation": "IU",
          "shortDisplayName": "Indiana"
        },
        "attributes": [],
        "guid": "632910e2-3f91-6653-eb91-50f286f9d8be",
        "alternativeId": "3904578",
        "headshot": {
          "href": "https://a.espncdn.com/i/headshots/womens-college-basketball/players/full/3904578.png"
        },
        "link": "https://www.espn.com/wnba/player/_/id/3904578/ali-patberg",
        "proLink": "https://www.espn.com/wnba/player/_/id/3904578/ali-patberg",
        "uid": "s:40~l:59~a:3904578"
      },
      "teamId": "5"
    },
    {
      "status": "SELECTION_MADE",
      "pick": 11,
      "overall": 35,
      "round": 3,
      "traded": false,
      "athlete": {
        "id": "106219",
        "displayName": "Faustine Aifuwa",
        "displayHeight": "6'5\"",
        "position": {
          "id": "9"
        },
        "team": {
          "location": "LSU",
          "name": "Tigers",
          "abbreviation": "LSU",
          "shortDisplayName": "LSU"
        },
        "attributes": [],
        "guid": "dbeec99d-a6ef-74d0-fdd3-e7681cc6f204",
        "alternativeId": "4065738",
        "headshot": {
          "href": "https://a.espncdn.com/i/headshots/womens-college-basketball/players/full/4065738.png"
        },
        "link": "https://www.espn.com/wnba/player/_/id/4065738/faustine-aifuwa",
        "proLink": "https://www.espn.com/wnba/player/_/id/4065738/faustine-aifuwa",
        "uid": "s:40~l:59~a:4065738"
      },
      "teamId": "17"
    },
    {
      "status": "SELECTION_MADE",
      "pick": 12,
      "overall": 36,
      "round": 3,
      "traded": false,
      "athlete": {
        "id": "106220",
        "displayName": "Kiara Smith",
        "displayHeight": "5'10\"",
        "position": {
          "id": "1"
        },
        "team": {
          "location": "Florida",
          "name": "Gators",
          "abbreviation": "FLA",
          "shortDisplayName": "Florida"
        },
        "attributes": [],
        "guid": "d94fad59-682c-8db4-26fe-73a6e6dda17b",
        "alternativeId": "4398629",
        "headshot": {
          "href": "https://a.espncdn.com/i/headshots/womens-college-basketball/players/full/4398629.png"
        },
        "link": "https://www.espn.com/wnba/player/_/id/4398629/kiara-smith",
        "proLink": "https://www.espn.com/wnba/player/_/id/4398629/kiara-smith",
        "uid": "s:40~l:59~a:4398629"
      },
      "teamId": "18"
    }
  ],
  "teams": [
    {
      "id": "20",
      "uid": "s:40~l:59~t:20",
      "location": "Atlanta",
      "name": "Dream",
      "abbreviation": "ATL",
      "displayName": "Atlanta Dream",
      "shortDisplayName": "Dream",
      "logo": "https://a.espncdn.com/i/teamlogos/wnba/500/atl.png",
      "darkLogo": "https://a.espncdn.com/i/teamlogos/wnba/500-dark/atl.png",
      "needs": [
        {
          "positionId": "9",
          "met": false
        },
        {
          "positionId": "6",
          "met": true
        },
        {
          "positionId": "2",
          "met": true
        }
      ],
      "link": "https://www.espn.com/wnba/draft/teams/_/name/atl/atlanta-dream",
      "record": {
        "season": 2021,
        "summary": "8-24",
        "standing": "5th in Eastern Conference"
      }
    },
    {
      "id": "19",
      "uid": "s:40~l:59~t:19",
      "location": "Chicago",
      "name": "Sky",
      "abbreviation": "CHI",
      "displayName": "Chicago Sky",
      "shortDisplayName": "Sky",
      "logo": "https://a.espncdn.com/i/teamlogos/wnba/500/chi.png",
      "darkLogo": "https://a.espncdn.com/i/teamlogos/wnba/500-dark/chi.png",
      "needs": [
        {
          "positionId": "5",
          "met": false
        },
        {
          "positionId": "6",
          "met": false
        },
        {
          "positionId": "2",
          "met": false
        }
      ],
      "link": "https://www.espn.com/wnba/draft/teams/_/name/chi/chicago-sky",
      "record": {
        "season": 2021,
        "summary": "16-16",
        "standing": "2nd in Eastern Conference"
      }
    },
    {
      "id": "18",
      "uid": "s:40~l:59~t:18",
      "location": "Connecticut",
      "name": "Sun",
      "abbreviation": "CON",
      "displayName": "Connecticut Sun",
      "shortDisplayName": "Sun",
      "logo": "https://a.espncdn.com/guid/7c72e7ee-5064-b766-2b39-95b57e3d9a08/logos/default.png",
      "darkLogo": "https://a.espncdn.com/guid/7c72e7ee-5064-b766-2b39-95b57e3d9a08/logos/default-dark.png",
      "needs": [
        {
          "positionId": "1",
          "met": true
        },
        {
          "positionId": "2",
          "met": true
        },
        {
          "positionId": "9",
          "met": false
        }
      ],
      "link": "https://www.espn.com/wnba/draft/teams/_/name/connecticu/connecticut-sun",
      "record": {
        "season": 2021,
        "summary": "26-6",
        "standing": "1st in Eastern Conference"
      }
    },
    {
      "id": "3",
      "uid": "s:40~l:59~t:3",
      "location": "Dallas",
      "name": "Wings",
      "abbreviation": "DAL",
      "displayName": "Dallas Wings",
      "shortDisplayName": "Wings",
      "logo": "https://a.espncdn.com/guid/34946ff8-281e-c57d-bb76-37fb1ebe3ec6/logos/default.png",
      "darkLogo": "https://a.espncdn.com/guid/34946ff8-281e-c57d-bb76-37fb1ebe3ec6/logos/default-dark.png",
      "needs": [
        {
          "positionId": "5",
          "met": true
        },
        {
          "positionId": "6",
          "met": true
        },
        {
          "positionId": "1",
          "met": true
        }
      ],
      "link": "https://www.espn.com/wnba/draft/teams/_/name/dallas/dallas-wings",
      "record": {
        "season": 2021,
        "summary": "14-18",
        "standing": "5th in Western Conference"
      }
    },
    {
      "id": "5",
      "uid": "s:40~l:59~t:5",
      "location": "Indiana",
      "name": "Fever",
      "abbreviation": "IND",
      "displayName": "Indiana Fever",
      "shortDisplayName": "Fever",
      "logo": "https://a.espncdn.com/i/teamlogos/wnba/500/ind.png",
      "darkLogo": "https://a.espncdn.com/i/teamlogos/wnba/500-dark/ind.png",
      "needs": [
        {
          "positionId": "6",
          "met": true
        },
        {
          "positionId": "9",
          "met": true
        },
        {
          "positionId": "5",
          "met": false
        }
      ],
      "link": "https://www.espn.com/wnba/draft/teams/_/name/ind/indiana-fever",
      "record": {
        "season": 2021,
        "summary": "6-26",
        "standing": "6th in Eastern Conference"
      }
    },
    {
      "id": "6",
      "uid": "s:40~l:59~t:6",
      "location": "Los Angeles",
      "name": "Sparks",
      "abbreviation": "LA",
      "displayName": "Los Angeles Sparks",
      "shortDisplayName": "Sparks",
      "logo": "https://a.espncdn.com/i/teamlogos/wnba/500/la.png",
      "darkLogo": "https://a.espncdn.com/i/teamlogos/wnba/500-dark/la.png",
      "needs": [
        {
          "positionId": "6",
          "met": true
        },
        {
          "positionId": "5",
          "met": true
        },
        {
          "positionId": "2",
          "met": true
        }
      ],
      "link": "https://www.espn.com/wnba/draft/teams/_/name/la/los-angeles-sparks",
      "record": {
        "season": 2021,
        "summary": "12-20",
        "standing": "6th in Western Conference"
      }
    },
    {
      "id": "17",
      "uid": "s:40~l:59~t:17",
      "location": "Las Vegas",
      "name": "Aces",
      "abbreviation": "LV",
      "displayName": "Las Vegas Aces",
      "shortDisplayName": "Aces",
      "logo": "https://a.espncdn.com/i/teamlogos/wnba/500/lv.png",
      "darkLogo": "https://a.espncdn.com/i/teamlogos/wnba/500-dark/lv.png",
      "needs": [
        {
          "positionId": "5",
          "met": true
        },
        {
          "positionId": "2",
          "met": true
        },
        {
          "positionId": "6",
          "met": false
        }
      ],
      "link": "https://www.espn.com/wnba/draft/teams/_/name/lv/las-vegas-aces",
      "record": {
        "season": 2021,
        "summary": "24-8",
        "standing": "1st in Western Conference"
      }
    },
    {
      "id": "8",
      "uid": "s:40~l:59~t:8",
      "location": "Minnesota",
      "name": "Lynx",
      "abbreviation": "MIN",
      "displayName": "Minnesota Lynx",
      "shortDisplayName": "Lynx",
      "logo": "https://a.espncdn.com/i/teamlogos/wnba/500/min.png",
      "darkLogo": "https://a.espncdn.com/i/teamlogos/wnba/500-dark/min.png",
      "needs": [
        {
          "positionId": "9",
          "met": false
        },
        {
          "positionId": "6",
          "met": true
        },
        {
          "positionId": "1",
          "met": false
        }
      ],
      "link": "https://www.espn.com/wnba/draft/teams/_/name/min/minnesota-lynx",
      "record": {
        "season": 2021,
        "summary": "22-10",
        "standing": "2nd in Western Conference"
      }
    },
    {
      "id": "9",
      "uid": "s:40~l:59~t:9",
      "location": "New York",
      "name": "Liberty",
      "abbreviation": "NY",
      "displayName": "New York Liberty",
      "shortDisplayName": "Liberty",
      "logo": "https://a.espncdn.com/i/teamlogos/wnba/500/ny.png",
      "darkLogo": "https://a.espncdn.com/i/teamlogos/wnba/500-dark/ny.png",
      "needs": [
        {
          "positionId": "9",
          "met": true
        },
        {
          "positionId": "5",
          "met": false
        },
        {
          "positionId": "2",
          "met": false
        }
      ],
      "link": "https://www.espn.com/wnba/draft/teams/_/name/ny/new-york-liberty",
      "record": {
        "season": 2021,
        "summary": "12-20",
        "standing": "3rd in Eastern Conference"
      }
    },
    {
      "id": "11",
      "uid": "s:40~l:59~t:11",
      "location": "Phoenix",
      "name": "Mercury",
      "abbreviation": "PHX",
      "displayName": "Phoenix Mercury",
      "shortDisplayName": "Mercury",
      "logo": "https://a.espncdn.com/i/teamlogos/wnba/500/scoreboard/phx.png",
      "darkLogo": "https://a.espncdn.com/i/teamlogos/wnba/500-dark/phx.png",
      "needs": [
        {
          "positionId": "6",
          "met": true
        },
        {
          "positionId": "5",
          "met": false
        },
        {
          "positionId": "9",
          "met": false
        }
      ],
      "link": "https://www.espn.com/wnba/draft/teams/_/name/phx/phoenix-mercury",
      "record": {
        "season": 2021,
        "summary": "19-13",
        "standing": "4th in Western Conference"
      }
    },
    {
      "id": "14",
      "uid": "s:40~l:59~t:14",
      "location": "Seattle",
      "name": "Storm",
      "abbreviation": "SEA",
      "displayName": "Seattle Storm",
      "shortDisplayName": "Storm",
      "logo": "https://a.espncdn.com/i/teamlogos/wnba/500/scoreboard/sea.png",
      "darkLogo": "https://a.espncdn.com/i/teamlogos/wnba/500-dark/scoreboard/sea.png",
      "needs": [
        {
          "positionId": "1",
          "met": true
        },
        {
          "positionId": "2",
          "met": false
        },
        {
          "positionId": "6",
          "met": true
        }
      ],
      "link": "https://www.espn.com/wnba/draft/teams/_/name/sea/seattle-storm",
      "record": {
        "season": 2021,
        "summary": "21-11",
        "standing": "3rd in Western Conference"
      }
    },
    {
      "id": "16",
      "uid": "s:40~l:59~t:16",
      "location": "Washington",
      "name": "Mystics",
      "abbreviation": "WSH",
      "displayName": "Washington Mystics",
      "shortDisplayName": "Mystics",
      "logo": "https://a.espncdn.com/i/teamlogos/wnba/500/scoreboard/wsh.png",
      "darkLogo": "https://a.espncdn.com/i/teamlogos/wnba/500-dark/scoreboard/wsh.png",
      "needs": [
        {
          "positionId": "6",
          "met": false
        },
        {
          "positionId": "9",
          "met": true
        },
        {
          "positionId": "1",
          "met": false
        }
      ],
      "link": "https://www.espn.com/wnba/draft/teams/_/name/wsh/washington-mystics",
      "record": {
        "season": 2021,
        "summary": "12-20",
        "standing": "4th in Eastern Conference"
      }
    }
  ]
}