{
"$ref": "http://sports.core.api.espn.com/v2/sports/basketball/leagues/wnba/athletes/145?lang=en&region=us",
"id": "145",
"uid": "s:40~l:59~a:145",
"guid": "2a83e622-c46c-a3ac-1d56-d182c667399a",
"type": "basketball",
"alternateIds": {
"sdr": "1871066"
},
"firstName": "Sylvia",
"lastName": "Crawley",
"fullName": "Sylvia Crawley",
"displayName": "Sylvia Crawley",
"shortName": "S. Crawley",
"weight": 187.0,
"displayWeight": "187 lbs",
"height": 77.0,
"displayHeight": "6' 5\"",
"age": 53,
"dateOfBirth": "1972-09-27T07:00Z",
"links": [
{
"language": "en-US",
"rel": [
"playercard",
"desktop",
"athlete"
],
"href": "https://www.espn.com/wnba/player/_/id/145/sylvia-crawley",
"text": "Player Card",
"shortText": "Player Card",
"isExternal": false,
"isPremium": false
},
{
"language": "en-US",
"rel": [
"stats",
"desktop",
"athlete"
],
"href": "https://www.espn.com/wnba/player/stats/_/id/145/sylvia-crawley",
"text": "Stats",
"shortText": "Stats",
"isExternal": false,
"isPremium": false
},
{
"language": "en-US",
"rel": [
"stats",
"sportscenter",
"app",
"athlete"
],
"href": "sportscenter://x-callback-url/showClubhouse?uid=s:40~l:59~a:145&section=stats",
"text": "Stats",
"shortText": "Stats",
"isExternal": false,
"isPremium": false
},
{
"language": "en-US",
"rel": [
"gamelog",
"desktop",
"athlete"
],
"href": "https://www.espn.com/wnba/player/gamelog/_/id/145/sylvia-crawley",
"text": "Game Log",
"shortText": "Game Log",
"isExternal": false,
"isPremium": false
},
{
"language": "en-US",
"rel": [
"gamelog",
"sportscenter",
"app",
"athlete"
],
"href": "sportscenter://x-callback-url/showClubhouse?uid=s:40~l:59~a:145&section=gamelog",
"text": "Game Log",
"shortText": "Game Log",
"isExternal": false,
"isPremium": false
},
{
"language": "en-US",
"rel": [
"news",
"desktop",
"athlete"
],
"href": "https://www.espn.com/wnba/player/news/_/id/145/sylvia-crawley",
"text": "News",
"shortText": "News",
"isExternal": false,
"isPremium": false
},
{
"language": "en-US",
"rel": [
"news",
"sportscenter",
"app",
"athlete"
],
"href": "sportscenter://x-callback-url/showClubhouse?uid=s:40~l:59~a:145&section=news",
"text": "News",
"shortText": "News",
"isExternal": false,
"isPremium": false
},
{
"language": "en-US",
"rel": [
"bio",
"desktop",
"athlete"
],
"href": "https://www.espn.com/wnba/player/bio/_/id/145/sylvia-crawley",
"text": "Bio",
"shortText": "Bio",
"isExternal": false,
"isPremium": false
},
{
"language": "en-US",
"rel": [
"bio",
"sportscenter",
"app",
"athlete"
],
"href": "sportscenter://x-callback-url/showClubhouse?uid=s:40~l:59~a:145&section=bio",
"text": "Bio",
"shortText": "Bio",
"isExternal": false,
"isPremium": false
},
{
"language": "en-US",
"rel": [
"overview",
"desktop",
"athlete"
],
"href": "https://www.espn.com/wnba/player/_/id/145/sylvia-crawley",
"text": "Overview",
"shortText": "Overview",
"isExternal": false,
"isPremium": false
},
{
"language": "en-US",
"rel": [
"overview",
"sportscenter",
"app",
"athlete"
],
"href": "sportscenter://x-callback-url/showClubhouse?uid=s:40~l:59~a:145",
"text": "Overview",
"shortText": "Overview",
"isExternal": false,
"isPremium": false
}
],
"birthPlace": {},
"college": {
"$ref": "http://sports.core.api.espn.com/v2/colleges/275?lang=en&region=us"
},
"slug": "sylvia-crawley",
"position": {
"$ref": "http://sports.core.api.espn.com/v2/sports/basketball/leagues/wnba/positions/0?lang=en&region=us",
"id": "0",
"name": "Not Available",
"displayName": "Not Available",
"abbreviation": "NA",
"leaf": false
},
"linked": true,
"statistics": {
"$ref": "http://sports.core.api.espn.com/v2/sports/basketball/leagues/wnba/athletes/145/statistics?lang=en&region=us"
},
"contracts": {
"$ref": "http://sports.core.api.espn.com/v2/sports/basketball/leagues/wnba/athletes/145/contracts?lang=en&region=us"
},
"active": false,
"status": {
"id": "2",
"name": "Inactive",
"type": "inactive",
"abbreviation": "Inactive"
},
"statisticslog": {
"$ref": "http://sports.core.api.espn.com/v2/sports/basketball/leagues/wnba/athletes/145/statisticslog?lang=en&region=us"
},
"seasons": {
"$ref": "http://sports.core.api.espn.com/v2/sports/basketball/leagues/wnba/athletes/145/seasons?lang=en&region=us"
}
}