{
"$ref": "http://sports.core.api.espn.com/v2/sports/basketball/leagues/wnba/athletes/4433795?lang=en&region=us",
"id": "4433795",
"uid": "s:40~l:59~a:4433795",
"guid": "96865a84-9cac-3ca0-9525-04367218dd7b",
"type": "basketball",
"alternateIds": {
"sdr": "4433795"
},
"firstName": "Sania",
"lastName": "Feagin",
"fullName": "Sania Feagin",
"displayName": "Sania Feagin",
"shortName": "S. Feagin",
"height": 75.0,
"displayHeight": "6' 3\"",
"age": 23,
"dateOfBirth": "2003-03-15T08:00Z",
"links": [
{
"language": "en-US",
"rel": [
"playercard",
"desktop",
"athlete"
],
"href": "https://www.espn.com/wnba/player/_/id/4433795/sania-feagin",
"text": "Player Card",
"shortText": "Player Card",
"isExternal": false,
"isPremium": false
},
{
"language": "en-US",
"rel": [
"stats",
"desktop",
"athlete"
],
"href": "https://www.espn.com/wnba/player/stats/_/id/4433795/sania-feagin",
"text": "Stats",
"shortText": "Stats",
"isExternal": false,
"isPremium": false
},
{
"language": "en-US",
"rel": [
"stats",
"sportscenter",
"app",
"athlete"
],
"href": "sportscenter://x-callback-url/showClubhouse?uid=s:40~l:59~a:4433795&section=stats",
"text": "Stats",
"shortText": "Stats",
"isExternal": false,
"isPremium": false
},
{
"language": "en-US",
"rel": [
"gamelog",
"desktop",
"athlete"
],
"href": "https://www.espn.com/wnba/player/gamelog/_/id/4433795/sania-feagin",
"text": "Game Log",
"shortText": "Game Log",
"isExternal": false,
"isPremium": false
},
{
"language": "en-US",
"rel": [
"gamelog",
"sportscenter",
"app",
"athlete"
],
"href": "sportscenter://x-callback-url/showClubhouse?uid=s:40~l:59~a:4433795&section=gamelog",
"text": "Game Log",
"shortText": "Game Log",
"isExternal": false,
"isPremium": false
},
{
"language": "en-US",
"rel": [
"news",
"desktop",
"athlete"
],
"href": "https://www.espn.com/wnba/player/news/_/id/4433795/sania-feagin",
"text": "News",
"shortText": "News",
"isExternal": false,
"isPremium": false
},
{
"language": "en-US",
"rel": [
"news",
"sportscenter",
"app",
"athlete"
],
"href": "sportscenter://x-callback-url/showClubhouse?uid=s:40~l:59~a:4433795&section=news",
"text": "News",
"shortText": "News",
"isExternal": false,
"isPremium": false
},
{
"language": "en-US",
"rel": [
"bio",
"desktop",
"athlete"
],
"href": "https://www.espn.com/wnba/player/bio/_/id/4433795/sania-feagin",
"text": "Bio",
"shortText": "Bio",
"isExternal": false,
"isPremium": false
},
{
"language": "en-US",
"rel": [
"bio",
"sportscenter",
"app",
"athlete"
],
"href": "sportscenter://x-callback-url/showClubhouse?uid=s:40~l:59~a:4433795&section=bio",
"text": "Bio",
"shortText": "Bio",
"isExternal": false,
"isPremium": false
},
{
"language": "en-US",
"rel": [
"overview",
"desktop",
"athlete"
],
"href": "https://www.espn.com/wnba/player/_/id/4433795/sania-feagin",
"text": "Overview",
"shortText": "Overview",
"isExternal": false,
"isPremium": false
},
{
"language": "en-US",
"rel": [
"overview",
"sportscenter",
"app",
"athlete"
],
"href": "sportscenter://x-callback-url/showClubhouse?uid=s:40~l:59~a:4433795",
"text": "Overview",
"shortText": "Overview",
"isExternal": false,
"isPremium": false
}
],
"birthPlace": {
"city": "Ellenwood",
"state": "GA",
"country": "USA"
},
"college": {
"$ref": "http://sports.core.api.espn.com/v2/colleges/2579?lang=en&region=us"
},
"slug": "sania-feagin",
"headshot": {
"href": "https://a.espncdn.com/i/headshots/wnba/players/full/4433795.png",
"alt": "Sania Feagin"
},
"position": {
"$ref": "http://sports.core.api.espn.com/v2/sports/basketball/leagues/wnba/positions/7?lang=en&region=us",
"id": "7",
"name": "Forward",
"displayName": "Forward",
"abbreviation": "F",
"leaf": false
},
"linked": true,
"team": {
"$ref": "http://sports.core.api.espn.com/v2/sports/basketball/leagues/wnba/seasons/2026/teams/132052?lang=en&region=us"
},
"statistics": {
"$ref": "http://sports.core.api.espn.com/v2/sports/basketball/leagues/wnba/athletes/4433795/statistics?lang=en&region=us"
},
"contracts": {
"$ref": "http://sports.core.api.espn.com/v2/sports/basketball/leagues/wnba/athletes/4433795/contracts?lang=en&region=us"
},
"experience": {
"years": 2
},
"collegeAthlete": {
"$ref": "http://sports.core.api.espn.com/v2/sports/basketball/leagues/womens-college-basketball/athletes/4433795?lang=en&region=us"
},
"active": true,
"draft": {
"displayText": "Year: 2025 Round: 2 Pick: 21",
"round": 2,
"year": 2025,
"selection": 21,
"team": {
"$ref": "http://sports.core.api.espn.com/v2/sports/basketball/leagues/wnba/seasons/2025/teams/6?lang=en&region=us"
}
},
"status": {
"id": "1",
"name": "Active",
"type": "active",
"abbreviation": "Active"
},
"statisticslog": {
"$ref": "http://sports.core.api.espn.com/v2/sports/basketball/leagues/wnba/athletes/4433795/statisticslog?lang=en&region=us"
},
"seasons": {
"$ref": "http://sports.core.api.espn.com/v2/sports/basketball/leagues/wnba/athletes/4433795/seasons?lang=en&region=us"
}
}