{
"$ref": "http://sports.core.api.espn.com/v2/sports/basketball/leagues/wnba/athletes/4898384?lang=en&region=us",
"id": "4898384",
"uid": "s:40~l:59~a:4898384",
"guid": "8c14caa5-a9c7-3508-aca8-567930a6d9b7",
"type": "basketball",
"alternateIds": {
"sdr": "4898384"
},
"firstName": "Kiki",
"lastName": "Iriafen",
"fullName": "Kiki Iriafen",
"displayName": "Kiki Iriafen",
"shortName": "K. Iriafen",
"height": 75.0,
"displayHeight": "6' 3\"",
"age": 22,
"dateOfBirth": "2003-08-26T07:00Z",
"links": [
{
"language": "en-US",
"rel": [
"playercard",
"desktop",
"athlete"
],
"href": "https://www.espn.com/wnba/player/_/id/4898384/kiki-iriafen",
"text": "Player Card",
"shortText": "Player Card",
"isExternal": false,
"isPremium": false
},
{
"language": "en-US",
"rel": [
"stats",
"desktop",
"athlete"
],
"href": "https://www.espn.com/wnba/player/stats/_/id/4898384/kiki-iriafen",
"text": "Stats",
"shortText": "Stats",
"isExternal": false,
"isPremium": false
},
{
"language": "en-US",
"rel": [
"stats",
"sportscenter",
"app",
"athlete"
],
"href": "sportscenter://x-callback-url/showClubhouse?uid=s:40~l:59~a:4898384&section=stats",
"text": "Stats",
"shortText": "Stats",
"isExternal": false,
"isPremium": false
},
{
"language": "en-US",
"rel": [
"gamelog",
"desktop",
"athlete"
],
"href": "https://www.espn.com/wnba/player/gamelog/_/id/4898384/kiki-iriafen",
"text": "Game Log",
"shortText": "Game Log",
"isExternal": false,
"isPremium": false
},
{
"language": "en-US",
"rel": [
"gamelog",
"sportscenter",
"app",
"athlete"
],
"href": "sportscenter://x-callback-url/showClubhouse?uid=s:40~l:59~a:4898384&section=gamelog",
"text": "Game Log",
"shortText": "Game Log",
"isExternal": false,
"isPremium": false
},
{
"language": "en-US",
"rel": [
"news",
"desktop",
"athlete"
],
"href": "https://www.espn.com/wnba/player/news/_/id/4898384/kiki-iriafen",
"text": "News",
"shortText": "News",
"isExternal": false,
"isPremium": false
},
{
"language": "en-US",
"rel": [
"news",
"sportscenter",
"app",
"athlete"
],
"href": "sportscenter://x-callback-url/showClubhouse?uid=s:40~l:59~a:4898384&section=news",
"text": "News",
"shortText": "News",
"isExternal": false,
"isPremium": false
},
{
"language": "en-US",
"rel": [
"bio",
"desktop",
"athlete"
],
"href": "https://www.espn.com/wnba/player/bio/_/id/4898384/kiki-iriafen",
"text": "Bio",
"shortText": "Bio",
"isExternal": false,
"isPremium": false
},
{
"language": "en-US",
"rel": [
"bio",
"sportscenter",
"app",
"athlete"
],
"href": "sportscenter://x-callback-url/showClubhouse?uid=s:40~l:59~a:4898384&section=bio",
"text": "Bio",
"shortText": "Bio",
"isExternal": false,
"isPremium": false
},
{
"language": "en-US",
"rel": [
"overview",
"desktop",
"athlete"
],
"href": "https://www.espn.com/wnba/player/_/id/4898384/kiki-iriafen",
"text": "Overview",
"shortText": "Overview",
"isExternal": false,
"isPremium": false
},
{
"language": "en-US",
"rel": [
"overview",
"sportscenter",
"app",
"athlete"
],
"href": "sportscenter://x-callback-url/showClubhouse?uid=s:40~l:59~a:4898384",
"text": "Overview",
"shortText": "Overview",
"isExternal": false,
"isPremium": false
}
],
"birthPlace": {
"city": "Los Angeles",
"state": "CA",
"country": "USA"
},
"college": {
"$ref": "http://sports.core.api.espn.com/v2/colleges/30?lang=en&region=us"
},
"slug": "kiki-iriafen",
"headshot": {
"href": "https://a.espncdn.com/i/headshots/wnba/players/full/4898384.png",
"alt": "Kiki Iriafen"
},
"jersey": "44",
"position": {
"$ref": "http://sports.core.api.espn.com/v2/sports/basketball/leagues/wnba/positions/7?lang=en&region=us",
"id": "7",
"name": "Forward",
"displayName": "Forward",
"abbreviation": "F",
"leaf": false
},
"linked": true,
"team": {
"$ref": "http://sports.core.api.espn.com/v2/sports/basketball/leagues/wnba/seasons/2026/teams/16?lang=en&region=us"
},
"statistics": {
"$ref": "http://sports.core.api.espn.com/v2/sports/basketball/leagues/wnba/athletes/4898384/statistics?lang=en&region=us"
},
"contracts": {
"$ref": "http://sports.core.api.espn.com/v2/sports/basketball/leagues/wnba/athletes/4898384/contracts?lang=en&region=us"
},
"experience": {
"years": 2
},
"collegeAthlete": {
"$ref": "http://sports.core.api.espn.com/v2/sports/basketball/leagues/womens-college-basketball/athletes/4898384?lang=en&region=us"
},
"active": true,
"draft": {
"displayText": "Year: 2025 Round: 1 Pick: 4",
"round": 1,
"year": 2025,
"selection": 4,
"team": {
"$ref": "http://sports.core.api.espn.com/v2/sports/basketball/leagues/wnba/seasons/2025/teams/16?lang=en&region=us"
}
},
"status": {
"id": "1",
"name": "Active",
"type": "active",
"abbreviation": "Active"
},
"statisticslog": {
"$ref": "http://sports.core.api.espn.com/v2/sports/basketball/leagues/wnba/athletes/4898384/statisticslog?lang=en&region=us"
},
"seasons": {
"$ref": "http://sports.core.api.espn.com/v2/sports/basketball/leagues/wnba/athletes/4898384/seasons?lang=en&region=us"
}
}