{
"$ref": "http://sports.core.api.espn.com/v2/sports/basketball/leagues/wnba/athletes/796?lang=en&region=us",
"id": "796",
"uid": "s:40~l:59~a:796",
"guid": "57bf49b7-1ec4-64e2-0d1f-e6ec941d61aa",
"type": "basketball",
"alternateIds": {
"sdr": "2171739"
},
"firstName": "Leilani",
"lastName": "Mitchell",
"fullName": "Leilani Mitchell",
"displayName": "Leilani Mitchell",
"shortName": "L. Mitchell",
"weight": 138.0,
"displayWeight": "138 lbs",
"height": 65.0,
"displayHeight": "5' 5\"",
"age": 41,
"dateOfBirth": "1985-06-15T07:00Z",
"links": [
{
"language": "en-US",
"rel": [
"playercard",
"desktop",
"athlete"
],
"href": "https://www.espn.com/wnba/player/_/id/796/leilani-mitchell",
"text": "Player Card",
"shortText": "Player Card",
"isExternal": false,
"isPremium": false
},
{
"language": "en-US",
"rel": [
"stats",
"desktop",
"athlete"
],
"href": "https://www.espn.com/wnba/player/stats/_/id/796/leilani-mitchell",
"text": "Stats",
"shortText": "Stats",
"isExternal": false,
"isPremium": false
},
{
"language": "en-US",
"rel": [
"stats",
"sportscenter",
"app",
"athlete"
],
"href": "sportscenter://x-callback-url/showClubhouse?uid=s:40~l:59~a:796&section=stats",
"text": "Stats",
"shortText": "Stats",
"isExternal": false,
"isPremium": false
},
{
"language": "en-US",
"rel": [
"gamelog",
"desktop",
"athlete"
],
"href": "https://www.espn.com/wnba/player/gamelog/_/id/796/leilani-mitchell",
"text": "Game Log",
"shortText": "Game Log",
"isExternal": false,
"isPremium": false
},
{
"language": "en-US",
"rel": [
"gamelog",
"sportscenter",
"app",
"athlete"
],
"href": "sportscenter://x-callback-url/showClubhouse?uid=s:40~l:59~a:796&section=gamelog",
"text": "Game Log",
"shortText": "Game Log",
"isExternal": false,
"isPremium": false
},
{
"language": "en-US",
"rel": [
"news",
"desktop",
"athlete"
],
"href": "https://www.espn.com/wnba/player/news/_/id/796/leilani-mitchell",
"text": "News",
"shortText": "News",
"isExternal": false,
"isPremium": false
},
{
"language": "en-US",
"rel": [
"news",
"sportscenter",
"app",
"athlete"
],
"href": "sportscenter://x-callback-url/showClubhouse?uid=s:40~l:59~a:796&section=news",
"text": "News",
"shortText": "News",
"isExternal": false,
"isPremium": false
},
{
"language": "en-US",
"rel": [
"bio",
"desktop",
"athlete"
],
"href": "https://www.espn.com/wnba/player/bio/_/id/796/leilani-mitchell",
"text": "Bio",
"shortText": "Bio",
"isExternal": false,
"isPremium": false
},
{
"language": "en-US",
"rel": [
"bio",
"sportscenter",
"app",
"athlete"
],
"href": "sportscenter://x-callback-url/showClubhouse?uid=s:40~l:59~a:796&section=bio",
"text": "Bio",
"shortText": "Bio",
"isExternal": false,
"isPremium": false
},
{
"language": "en-US",
"rel": [
"overview",
"desktop",
"athlete"
],
"href": "https://www.espn.com/wnba/player/_/id/796/leilani-mitchell",
"text": "Overview",
"shortText": "Overview",
"isExternal": false,
"isPremium": false
},
{
"language": "en-US",
"rel": [
"overview",
"sportscenter",
"app",
"athlete"
],
"href": "sportscenter://x-callback-url/showClubhouse?uid=s:40~l:59~a:796",
"text": "Overview",
"shortText": "Overview",
"isExternal": false,
"isPremium": false
}
],
"birthPlace": {
"city": "Richland",
"state": "WA",
"country": "USA"
},
"college": {
"$ref": "http://sports.core.api.espn.com/v2/colleges/254?lang=en&region=us"
},
"slug": "leilani-mitchell",
"headshot": {
"href": "https://a.espncdn.com/i/headshots/wnba/players/full/796.png",
"alt": "Leilani Mitchell"
},
"jersey": "5",
"position": {
"$ref": "http://sports.core.api.espn.com/v2/sports/basketball/leagues/wnba/positions/3?lang=en&region=us",
"id": "3",
"name": "Guard",
"displayName": "Guard",
"abbreviation": "G",
"leaf": false
},
"linked": true,
"team": {
"$ref": "http://sports.core.api.espn.com/v2/sports/basketball/leagues/wnba/seasons/2021/teams/16?lang=en&region=us"
},
"statistics": {
"$ref": "http://sports.core.api.espn.com/v2/sports/basketball/leagues/wnba/athletes/796/statistics?lang=en&region=us"
},
"contracts": {
"$ref": "http://sports.core.api.espn.com/v2/sports/basketball/leagues/wnba/athletes/796/contracts?lang=en&region=us"
},
"experience": {
"years": 12
},
"collegeAthlete": {
"$ref": "http://sports.core.api.espn.com/v2/sports/basketball/leagues/womens-college-basketball/athletes/2171739?lang=en&region=us"
},
"active": false,
"draft": {
"displayText": "Year: 2008 Round: 2 Pick: 25",
"round": 2,
"year": 2008,
"selection": 25,
"team": {
"$ref": "http://sports.core.api.espn.com/v2/sports/basketball/leagues/wnba/seasons/2008/teams/11?lang=en&region=us"
}
},
"status": {
"id": "2",
"name": "Inactive",
"type": "inactive",
"abbreviation": "Inactive"
},
"statisticslog": {
"$ref": "http://sports.core.api.espn.com/v2/sports/basketball/leagues/wnba/athletes/796/statisticslog?lang=en&region=us"
},
"seasons": {
"$ref": "http://sports.core.api.espn.com/v2/sports/basketball/leagues/wnba/athletes/796/seasons?lang=en&region=us"
}
}